huaweicloudsdkscm/__init__.py
huaweicloudsdkscm/v3/__init__.py
huaweicloudsdkscm/v3/scm_async_client.py
huaweicloudsdkscm/v3/scm_client.py
huaweicloudsdkscm/v3/model/__init__.py
huaweicloudsdkscm/v3/model/apply_certificate_request.py
huaweicloudsdkscm/v3/model/apply_certificate_request_body.py
huaweicloudsdkscm/v3/model/apply_certificate_response.py
huaweicloudsdkscm/v3/model/authentification.py
huaweicloudsdkscm/v3/model/batch_create_or_delete_tags_request.py
huaweicloudsdkscm/v3/model/batch_create_or_delete_tags_request_body.py
huaweicloudsdkscm/v3/model/batch_create_or_delete_tags_response.py
huaweicloudsdkscm/v3/model/batch_push_certificate_request.py
huaweicloudsdkscm/v3/model/batch_push_certificate_request_body.py
huaweicloudsdkscm/v3/model/batch_push_certificate_response.py
huaweicloudsdkscm/v3/model/batch_push_certificate_response_body_results.py
huaweicloudsdkscm/v3/model/cancel_certificate_request_request.py
huaweicloudsdkscm/v3/model/cancel_certificate_request_response.py
huaweicloudsdkscm/v3/model/cert_detail.py
huaweicloudsdkscm/v3/model/certificate_detail.py
huaweicloudsdkscm/v3/model/create_certificate_tag_request.py
huaweicloudsdkscm/v3/model/create_certificate_tag_request_body.py
huaweicloudsdkscm/v3/model/create_certificate_tag_response.py
huaweicloudsdkscm/v3/model/create_csr_request.py
huaweicloudsdkscm/v3/model/create_csr_request_body.py
huaweicloudsdkscm/v3/model/create_csr_response.py
huaweicloudsdkscm/v3/model/csr_response_body.py
huaweicloudsdkscm/v3/model/delete_certificate_request.py
huaweicloudsdkscm/v3/model/delete_certificate_response.py
huaweicloudsdkscm/v3/model/delete_csr_request.py
huaweicloudsdkscm/v3/model/delete_csr_response.py
huaweicloudsdkscm/v3/model/deploy_certificate_request.py
huaweicloudsdkscm/v3/model/deploy_certificate_request_body.py
huaweicloudsdkscm/v3/model/deploy_certificate_response.py
huaweicloudsdkscm/v3/model/deployed_resource.py
huaweicloudsdkscm/v3/model/deployed_resource_detail.py
huaweicloudsdkscm-3.1.184.dist-info/METADATA
huaweicloudsdkscm-3.1.184.dist-info/WHEEL
huaweicloudsdkscm-3.1.184.dist-info/licenses/LICENSE
huaweicloudsdkscm-3.1.184.dist-info/RECORD
